RevPyKit/RevPyKit.py
RevPyKit/__init__.py
RevPyKit/tab1_Analysis.py
RevPyKit/tab1_Analysis_PE.py
RevPyKit/tab2_HexEditor.py
RevPyKit/tab3_Example.py
RevPyKit/images/55aa.png
revpykit-0.1.0.dist-info/METADATA
revpykit-0.1.0.dist-info/WHEEL
revpykit-0.1.0.dist-info/licenses/LICENSE
revpykit-0.1.0.dist-info/RECORD
