Metadata-Version: 2.3
Name: RevPyKit
Version: 0.1.0
Summary: RevPyKit is a reverse engineering toolkit written in Python. It is an extendable platform which currently supports hashing, file signature detection, string searches, hex editing, and Windows PE analysis.
Project-URL: Homepage, https://github.com/FiftyFiveAA/RevPyKit/
Project-URL: Issues, https://github.com/FiftyFiveAA/RevPyKit/issues
Author-email: FiftyFiveAA <fiftyfiveaa@gmail.com>
License-File: LICENSE
Classifier: License :: OSI Approved :: GNU General Public License v3 (GPLv3)
Classifier: Operating System :: OS Independent
Classifier: Programming Language :: Python :: 3
Requires-Python: >=3.8
